tornado_logging_slack
