Metadata-Version: 1.0
Name: tornado-logging-slack
Version: 0.2.1
Summary: Log tornado in slack chat without block eventloop
Home-page: https://github.com/globocom/tornado-logging-slack
Author: Globo.com
Author-email: backstage1@corp.globo.com
License: MIT
Keywords: tornado slack logging
Platform: any
